[
    {"id": 1, "name": "Micro-Bot A", "type": "Robot", "power": 1, "points": 1, "symbols": ["Nut"], "beltSpeed": 1},
    {"id": 2, "name": "Micro-Bot B", "type": "Robot", "power": 1, "points": 1, "symbols": ["Oil"], "beltSpeed": 1},
    {"id": 3, "name": "Micro-Bot C", "type": "Robot", "power": 1, "points": 1, "symbols": ["Cog"], "beltSpeed": 1},
    {"id": 4, "name": "Micro-Bot D", "type": "Robot", "power": 1, "points": 1, "symbols": ["Bolt"], "beltSpeed": 1},
    {"id": 5, "name": "Rusty Scrapper", "type": "Robot", "power": 1, "points": 2, "symbols": ["Nut"], "beltSpeed": 2},
    {"id": 6, "name": "Rusty Scrapper", "type": "Robot", "power": 1, "points": 2, "symbols": ["Oil"], "beltSpeed": 2},
    {"id": 7, "name": "Minor Helper", "type": "Robot", "power": 1, "points": 1, "symbols": ["Cog"], "beltSpeed": 1},
    {"id": 8, "name": "Minor Helper", "type": "Robot", "power": 1, "points": 1, "symbols": ["Bolt"], "beltSpeed": 1},
    {"id": 9, "name": "Tin Can", "type": "Robot", "power": 1, "points": 0, "symbols": ["Nut", "Oil"], "beltSpeed": 1},
    {"id": 10, "name": "Tin Can", "type": "Robot", "power": 1, "points": 0, "symbols": ["Cog", "Bolt"], "beltSpeed": 1},
    {"id": 11, "name": "Sparky", "type": "Robot", "power": 1, "points": 1, "symbols": ["Oil"], "beltSpeed": 2},
    {"id": 12, "name": "Sparky", "type": "Robot", "power": 1, "points": 1, "symbols": ["Nut"], "beltSpeed": 2},
    {"id": 13, "name": "Workhorse", "type": "Robot", "power": 2, "points": 2, "symbols": ["Nut", "Bolt"], "beltSpeed": 2},
    {"id": 14, "name": "Workhorse", "type": "Robot", "power": 2, "points": 2, "symbols": ["Oil", "Cog"], "beltSpeed": 2},
    {"id": 15, "name": "Welder-Bot", "type": "Robot", "power": 2, "points": 3, "symbols": ["Bolt"], "beltSpeed": 3},
    {"id": 16, "name": "Welder-Bot", "type": "Robot", "power": 2, "points": 3, "symbols": ["Cog"], "beltSpeed": 3},
    {"id": 17, "name": "Standard unit", "type": "Robot", "power": 2, "points": 2, "symbols": ["Oil"], "beltSpeed": 2},
    {"id": 18, "name": "Standard unit", "type": "Robot", "power": 2, "points": 2, "symbols": ["Nut"], "beltSpeed": 2},
    {"id": 19, "name": "Tread-Bot", "type": "Robot", "power": 2, "points": 1, "symbols": ["Nut", "Oil", "Cog"], "beltSpeed": 1},
    {"id": 20, "name": "Tread-Bot", "type": "Robot", "power": 2, "points": 1, "symbols": ["Bolt", "Oil", "Cog"], "beltSpeed": 1},
    {"id": 21, "name": "Heavy Lifter", "type": "Robot", "power": 3, "points": 4, "symbols": ["Nut", "Cog"], "beltSpeed": 3},
    {"id": 22, "name": "Heavy Lifter", "type": "Robot", "power": 3, "points": 4, "symbols": ["Bolt", "Oil"], "beltSpeed": 3},
    {"id": 23, "name": "Factory Guard", "type": "Robot", "power": 3, "points": 5, "symbols": ["Bolt"], "beltSpeed": 4},
    {"id": 24, "name": "Factory Guard", "type": "Robot", "power": 3, "points": 5, "symbols": ["Cog"], "beltSpeed": 4},
    {"id": 25, "name": "Steam-Bot", "type": "Robot", "power": 3, "points": 3, "symbols": ["Nut", "Oil"], "beltSpeed": 2},
    {"id": 26, "name": "Steam-Bot", "type": "Robot", "power": 3, "points": 3, "symbols": ["Bolt", "Cog"], "beltSpeed": 2},
    {"id": 27, "name": "Advanced Drone", "type": "Robot", "power": 3, "points": 2, "symbols": ["Nut", "Oil", "Cog", "Bolt"], "beltSpeed": 1},
    {"id": 28, "name": "Advanced Drone", "type": "Robot", "power": 3, "points": 2, "symbols": ["Nut", "Oil", "Cog", "Bolt"], "beltSpeed": 1},
    {"id": 29, "name": "Elite Worker", "type": "Robot", "power": 4, "points": 6, "symbols": ["Nut", "Bolt"], "beltSpeed": 4},
    {"id": 30, "name": "Elite Worker", "type": "Robot", "power": 4, "points": 6, "symbols": ["Oil", "Cog"], "beltSpeed": 4},
    {"id": 31, "name": "Super-Bot", "type": "Robot", "power": 4, "points": 7, "symbols": ["Cog", "Bolt"], "beltSpeed": 8},
    {"id": 32, "name": "Super-Bot", "type": "Robot", "power": 4, "points": 7, "symbols": ["Nut", "Oil"], "beltSpeed": 8},
    {"id": 33, "name": "The Chief", "type": "Robot", "power": 5, "points": 8, "symbols": ["Nut", "Oil", "Cog"], "beltSpeed": 8},
    {"id": 34, "name": "The Chief", "type": "Robot", "power": 5, "points": 8, "symbols": ["Nut", "Bolt", "Cog"], "beltSpeed": 8},
    {"id": 35, "name": "Mega-Bot", "type": "Robot", "power": 5, "points": 10, "symbols": ["Bolt"], "beltSpeed": 4},
    {"id": 36, "name": "Mega-Bot", "type": "Robot", "power": 5, "points": 10, "symbols": ["Oil"], "beltSpeed": 4},
    {"id": 37, "name": "System Upgrade", "type": "Robot", "power": 0, "points": 2, "symbols": ["Nut", "Oil", "Cog", "Bolt"], "beltSpeed": 2},
    {"id": 38, "name": "Armor Plate", "type": "Robot", "power": 0, "points": 2, "symbols": ["Nut", "Oil", "Cog", "Bolt"], "beltSpeed": 2},
    {"id": 39, "name": "Fzzzt!", "type": "Fzzzt", "power": 3, "points": -1, "symbols": [], "beltSpeed": 1},
    {"id": 40, "name": "Fzzzt!", "type": "Fzzzt", "power": 3, "points": -1, "symbols": [], "beltSpeed": 1},
    {"id": 41, "name": "Fzzzt!", "type": "Fzzzt", "power": 3, "points": -1, "symbols": [], "beltSpeed": 1},
    {"id": 42, "name": "Fzzzt!", "type": "Fzzzt", "power": 3, "points": -1, "symbols": [], "beltSpeed": 1},
    {"id": 43, "name": "Prototype Unit", "type": "ProductionUnit", "power": 0, "points": 0, "recipe": {"Nut": 1}, "bonusPerWidget": 3, "penalty": 3},
    {"id": 44, "name": "Prototype Unit", "type": "ProductionUnit", "power": 0, "points": 0, "recipe": {"Oil": 1}, "bonusPerWidget": 3, "penalty": 3},
    {"id": 45, "name": "Enhanced Unit", "type": "ProductionUnit", "power": 0, "points": 0, "recipe": {"Nut": 1, "Oil": 1}, "bonusPerWidget": 6, "penalty": 4},
    {"id": 46, "name": "Enhanced Unit", "type": "ProductionUnit", "power": 0, "points": 0, "recipe": {"Cog": 1, "Bolt": 1}, "bonusPerWidget": 6, "penalty": 4},
    {"id": 47, "name": "Advanced Unit", "type": "ProductionUnit", "power": 0, "points": 0, "recipe": {"Nut": 1, "Cog": 1, "Bolt": 1}, "bonusPerWidget": 9, "penalty": 5},
    {"id": 48, "name": "Advanced Unit", "type": "ProductionUnit", "power": 0, "points": 0, "recipe": {"Oil": 1, "Cog": 1, "Bolt": 1}, "bonusPerWidget": 9, "penalty": 5},
    {"id": 49, "name": "Supreme Unit", "type": "ProductionUnit", "power": 0, "points": 0, "recipe": {"Nut": 1, "Oil": 1, "Cog": 1, "Bolt": 1}, "bonusPerWidget": 12, "penalty": 6},
    {"id": 50, "name": "Supreme Unit", "type": "ProductionUnit", "power": 0, "points": 0, "recipe": {"Nut": 1, "Oil": 1, "Cog": 1, "Bolt": 1}, "bonusPerWidget": 12, "penalty": 6},
    {"id": 51, "name": "Mass Producer", "type": "ProductionUnit", "power": 0, "points": 0, "recipe": {"Nut": 2, "Bolt": 2}, "bonusPerWidget": 15, "penalty": 8},
    {"id": 52, "name": "Oil Refinery", "type": "ProductionUnit", "power": 0, "points": 0, "recipe": {"Oil": 3}, "bonusPerWidget": 10, "penalty": 5}
  ]